{
  "version": 1,
  "dependencies": [
    {
      "source": {
        "git": {
          "remote": "https://github.com/grafana/grafonnet-lib.git",
          "subdir": "grafonnet"
        }
      },
      "version": "a1d61cce1da59c71409b99b5c7568511fec661ea",
      "sum": "342u++/7rViR/zj2jeJOjshzglkZ1SY+hFNuyCBFMdc="
    },
    {
      "source": {
        "git": {
          "remote": "https://github.com/grafana/jsonnet-libs.git",
          "subdir": "grafana-builder"
        }
      },
      "version": "21526e83f442793d5a0c5969867d123915422b79",
      "sum": "5ku1Hd8UPnjmn8nWyaTFzMpT3Pa+VylBnmposMSVEuU="
    },
    {
      "source": {
        "git": {
          "remote": "https://github.com/prometheus/prometheus.git",
          "subdir": "documentation/prometheus-mixin"
        }
      },
      "version": "ee7e105d313ab527f0036c44af46925db6ee3de6",
      "sum": "u/Fpz2MPkezy71/q+c7mF0vc3hE9fWt2W/YbvF0LP/8="
    }
  ],
  "legacyImports": false
}
