{
  "version": 1,
  "dependencies": [
    {
      "source": {
        "git": {
          "remote": "https://github.com/grafana/grafonnet.git",
          "subdir": "gen/grafonnet-v11.0.0"
        }
      },
      "version": "d20e609202733790caf5b554c9945d049f243ae3",
      "sum": "0BvzR0i4bS4hc2O3xDv6i9m52z7mPrjvqxtcPrGhynA="
    },
    {
      "source": {
        "git": {
          "remote": "https://github.com/grafana/jsonnet-libs.git",
          "subdir": "common-lib"
        }
      },
      "version": "09ca0a6735fa87a36cccd2e74fb9734eb0a88ac4",
      "sum": "pYKpfusfes8YzZwdc4V4RHBiSaRJGcVZb9PTP6ix6bs="
    },
    {
      "source": {
        "git": {
          "remote": "https://github.com/grafana/jsonnet-libs.git",
          "subdir": "jvm-observ-lib"
        }
      },
      "version": "09ca0a6735fa87a36cccd2e74fb9734eb0a88ac4",
      "sum": "igcbO0tudOBEfL6yjKI259Rdf/ykJOu03nClOncxo6Q="
    },
    {
      "source": {
        "git": {
          "remote": "https://github.com/grafana/jsonnet-libs.git",
          "subdir": "kafka-mixin"
        }
      },
      "version": "09ca0a6735fa87a36cccd2e74fb9734eb0a88ac4",
      "sum": "VGfYNhHiMr5XOQIZVM+G10Djpi+VnN5bpKn33ggYMhw="
    },
    {
      "source": {
        "git": {
          "remote": "https://github.com/grafana/jsonnet-libs.git",
          "subdir": "kafka-observ-lib"
        }
      },
      "version": "09ca0a6735fa87a36cccd2e74fb9734eb0a88ac4",
      "sum": "63veDcZzQapbabKRu5yA57uQE3H5tMw0HY3WiMVvLdk="
    },
    {
      "source": {
        "git": {
          "remote": "https://github.com/grafana/jsonnet-libs.git",
          "subdir": "process-observ-lib"
        }
      },
      "version": "09ca0a6735fa87a36cccd2e74fb9734eb0a88ac4",
      "sum": "3FdC5zroOR8KKrPY8Q+PWeq//d9RJS27tX/OB8+sLfY="
    },
    {
      "source": {
        "git": {
          "remote": "https://github.com/grafana/jsonnet-libs.git",
          "subdir": "zookeeper-observ-lib"
        }
      },
      "version": "09ca0a6735fa87a36cccd2e74fb9734eb0a88ac4",
      "sum": "V4BR7+q996VlrcaKw4GDs3o5/9fvcJh5/EHT7kq55Ms="
    },
    {
      "source": {
        "git": {
          "remote": "https://github.com/jsonnet-libs/docsonnet.git",
          "subdir": "doc-util"
        }
      },
      "version": "6ac6c69685b8c29c54515448eaca583da2d88150",
      "sum": "BrAL/k23jq+xy9oA7TWIhUx07dsA/QLm3g7ktCwe//U="
    },
    {
      "source": {
        "git": {
          "remote": "https://github.com/jsonnet-libs/xtd.git",
          "subdir": ""
        }
      },
      "version": "1199b50e9d2ff53d4bb5fb2304ad1fb69d38e609",
      "sum": "LfbgcJbilu4uBdKYZSvmkoOTPwEAzg10L3/VqKAIWtA="
    },
    {
      "source": {
        "git": {
          "remote": "https://github.com/yugui/jsonnetunit.git",
          "subdir": "jsonnetunit"
        }
      },
      "version": "6927c58cae7624a00f368b977ccc477d4f74071f",
      "sum": "9FFqqln65hooRF0l6rjICDtnTxUlmDj34+sKMh4sjPI="
    }
  ],
  "legacyImports": false
}
